{"rtu_count": 2, "nodes": [{"id": "b19", "rtu": "0", "type": "bus"}, {"id": "b20", "rtu": "0", "type": "bus"}, {"id": "b22", "rtu": "0", "type": "bus"}, {"id": "b23", "rtu": "0", "type": "bus"}, {"id": "s3", "type": "switch", "rtu": "0"}, {"id": "sensor_13", "type": "meter", "rtu": "0"}, {"id": "sensor_14", "type": "meter", "rtu": "0"}, {"id": "sensor_16", "type": "meter", "rtu": "0"}, {"id": "sensor_17", "type": "meter", "rtu": "0"}, {"id": "sensor_18", "type": "meter", "rtu": "0"}, {"id": "sensor_15", "type": "meter", "rtu": "0"}, {"id": "sensor_19", "type": "meter", "rtu": "0"}, {"id": "sensor_20", "type": "meter", "rtu": "0"}, {"id": "sensor_21", "type": "meter", "rtu": "0"}, {"id": "sensor_22", "type": "meter", "rtu": "0"}, {"id": "sensor_23", "type": "meter", "rtu": "0"}, {"id": "sensor_24", "type": "meter", "rtu": "0"}, {"id": "b27", "rtu": "1", "type": "bus"}, {"id": "b26", "rtu": "1", "type": "bus"}, {"id": "b25", "rtu": "1", "type": "bus"}, {"id": "b24", "rtu": "1", "type": "bus"}, {"id": "s1", "type": "switch", "rtu": "1"}, {"id": "s2", "type": "switch", "rtu": "1"}, {"id": "sensor_1", "type": "meter", "rtu": "1"}, {"id": "sensor_2", "type": "meter", "rtu": "1"}, {"id": "sensor_3", "type": "meter", "rtu": "1"}, {"id": "sensor_4", "type": "meter", "rtu": "1"}, {"id": "sensor_5", "type": "meter", "rtu": "1"}, {"id": "sensor_6", "type": "meter", "rtu": "1"}, {"id": "sensor_7", "type": "meter", "rtu": "1"}, {"id": "sensor_8", "type": "meter", "rtu": "1"}, {"id": "sensor_9", "type": "meter", "rtu": "1"}, {"id": "sensor_10", "type": "meter", "rtu": "1"}, {"id": "sensor_11", "type": "meter", "rtu": "1"}, {"id": "sensor_12", "type": "meter", "rtu": "1"}], "links": [{"id": 0, "identifier": "branch_40_0", "source": "b24", "target": "sensor_12"}, {"id": 1, "identifier": "branch_40_1", "source": "sensor_12", "target": "sensor_13"}, {"id": 2, "identifier": "branch_40_2", "source": "sensor_13", "target": "sensor_14"}, {"id": 3, "identifier": "branch_40_3", "source": "sensor_14", "target": "b19"}, {"id": 4, "identifier": "branch_38_0", "source": "b19", "target": "sensor_17"}, {"id": 5, "identifier": "branch_38_1", "source": "sensor_17", "target": "sensor_22"}, {"id": 6, "identifier": "branch_38_2", "source": "sensor_22", "target": "b23"}, {"id": 7, "identifier": "branch_31_0", "source": "b23", "target": "sensor_23"}, {"id": 8, "identifier": "branch_31_1", "source": "sensor_23", "target": "s2"}, {"id": 9, "identifier": "branch_31_2", "source": "s2", "target": "sensor_11"}, {"id": 10, "identifier": "branch_31_3", "source": "sensor_11", "target": "b24"}, {"id": 11, "identifier": "branch_39_0", "source": "b23", "target": "sensor_24"}, {"id": 12, "identifier": "branch_39_1", "source": "sensor_24", "target": "sensor_10"}, {"id": 13, "identifier": "branch_39_2", "source": "sensor_10", "target": "b24"}, {"id": 14, "identifier": "branch_30_0", "source": "b22", "target": "sensor_20"}, {"id": 15, "identifier": "branch_30_1", "source": "sensor_20", "target": "sensor_21"}, {"id": 16, "identifier": "branch_30_2", "source": "sensor_21", "target": "b23"}, {"id": 17, "identifier": "branch_28_0", "source": "b20", "target": "sensor_15"}, {"id": 18, "identifier": "branch_28_1", "source": "sensor_15", "target": "sensor_19"}, {"id": 19, "identifier": "branch_28_2", "source": "sensor_19", "target": "b22"}, {"id": 20, "identifier": "branch_27_0", "source": "b19", "target": "s3"}, {"id": 21, "identifier": "branch_27_1", "source": "s3", "target": "sensor_16"}, {"id": 22, "identifier": "branch_27_2", "source": "sensor_16", "target": "sensor_18"}, {"id": 23, "identifier": "branch_27_3", "source": "sensor_18", "target": "b20"}, {"id": 24, "identifier": "branch_35_0", "source": "sensor_1", "target": "b27"}, {"id": 25, "identifier": "branch_34_0", "source": "b26", "target": "sensor_4"}, {"id": 26, "identifier": "branch_34_1", "source": "sensor_4", "target": "sensor_3"}, {"id": 27, "identifier": "branch_34_2", "source": "sensor_3", "target": "b27"}, {"id": 28, "identifier": "branch_37_0", "source": "b27", "target": "sensor_2"}, {"id": 29, "identifier": "branch_37_1", "source": "sensor_2", "target": "s1"}, {"id": 30, "identifier": "branch_37_2", "source": "s1", "target": "sensor_7"}, {"id": 31, "identifier": "branch_37_3", "source": "sensor_7", "target": "b25"}, {"id": 32, "identifier": "branch_33_0", "source": "b25", "target": "sensor_6"}, {"id": 33, "identifier": "branch_33_1", "source": "sensor_6", "target": "sensor_5"}, {"id": 34, "identifier": "branch_33_2", "source": "sensor_5", "target": "b26"}, {"id": 35, "identifier": "branch_32_0", "source": "b25", "target": "sensor_8"}, {"id": 36, "identifier": "branch_32_1", "source": "sensor_8", "target": "sensor_9"}, {"id": 37, "identifier": "branch_32_2", "source": "sensor_9", "target": "b24"}]}